{
  "animateLoading": true,
  "borderRadius": "{{appsmith.theme.borderRadius.appBorderRadius}}",
  "bottomRow": 690,
  "boxShadow": "none",
  "canEscapeKeyClose": true,
  "canOutsideClickClose": true,
  "children": [
    {
      "borderRadius": "{{appsmith.theme.borderRadius.appBorderRadius}}",
      "bottomRow": 660,
      "boxShadow": "{{appsmith.theme.boxShadow.appBoxShadow}}",
      "canExtend": true,
      "detachFromLayout": true,
      "dynamicBindingPathList": [
        {
          "key": "borderRadius"
        },
        {
          "key": "boxShadow"
        }
      ],
      "dynamicHeight": "AUTO_HEIGHT",
      "flexLayers": [],
      "isDisabled": false,
      "isLoading": false,
      "isVisible": true,
      "key": "x5uohs7z0d",
      "leftColumn": 0,
      "maxDynamicHeight": 9000,
      "minDynamicHeight": 4,
      "minHeight": 660,
      "minWidth": 450,
      "mobileBottomRow": 240,
      "mobileLeftColumn": 0,
      "mobileRightColumn": 486,
      "mobileTopRow": 0,
      "needsErrorInfo": false,
      "parentColumnSpace": 1,
      "parentId": "54rae2hacu",
      "parentRowSpace": 1,
      "renderMode": "CANVAS",
      "responsiveBehavior": "fill",
      "rightColumn": 486,
      "shouldScrollContents": false,
      "topRow": 0,
      "type": "CANVAS_WIDGET",
      "version": 1,
      "widgetId": "q1j91apsj1",
      "widgetName": "Canvas2"
    }
  ],
  "detachFromLayout": true,
  "dynamicBindingPathList": [
    {
      "key": "borderRadius"
    }
  ],
  "dynamicHeight": "AUTO_HEIGHT",
  "height": 660,
  "isCanvas": true,
  "isLoading": false,
  "key": "okfsu8qb75",
  "leftColumn": 10,
  "maxDynamicHeight": 9000,
  "minDynamicHeight": 24,
  "minHeight": 660,
  "mobileBottomRow": 54,
  "mobileLeftColumn": 10,
  "mobileRightColumn": 34,
  "mobileTopRow": 30,
  "needsErrorInfo": false,
  "parentColumnSpace": 20.25,
  "parentId": "0",
  "parentRowSpace": 10,
  "renderMode": "CANVAS",
  "rightColumn": 34,
  "shouldScrollContents": true,
  "topRow": 30,
  "type": "MODAL_WIDGET",
  "version": 2,
  "widgetId": "54rae2hacu",
  "widgetName": "adjustContactModal",
  "width": 994
}